scs4onnx/__init__.py
scs4onnx/__main__.py
scs4onnx/onnx_shrink_constant.py
scs4onnx-1.0.18.dist-info/LICENSE
scs4onnx-1.0.18.dist-info/METADATA
scs4onnx-1.0.18.dist-info/WHEEL
scs4onnx-1.0.18.dist-info/entry_points.txt
scs4onnx-1.0.18.dist-info/top_level.txt
scs4onnx-1.0.18.dist-info/RECORD
